cadenzaanalytics/__init__.py
cadenzaanalytics/cadenza_analytics_extension.py
cadenzaanalytics/cadenza_analytics_extension_service.py
cadenzaanalytics/data/__init__.py
cadenzaanalytics/data/analytics_extension.py
cadenzaanalytics/data/attribute_group.py
cadenzaanalytics/data/attribute_role.py
cadenzaanalytics/data/column_metadata.py
cadenzaanalytics/data/data_container_metadata.py
cadenzaanalytics/data/data_object.py
cadenzaanalytics/data/data_type.py
cadenzaanalytics/data/extension_type.py
cadenzaanalytics/data/geometry_type.py
cadenzaanalytics/data/measure_aggregation.py
cadenzaanalytics/data/parameter.py
cadenzaanalytics/data/parameter_type.py
cadenzaanalytics/data/parameter_value.py
cadenzaanalytics/data/table.py
cadenzaanalytics/request/__init__.py
cadenzaanalytics/request/analytics_request.py
cadenzaanalytics/request/request_metadata.py
cadenzaanalytics/request/request_parameter.py
cadenzaanalytics/request/request_table.py
cadenzaanalytics/request/view_parameter.py
cadenzaanalytics/response/__init__.py
cadenzaanalytics/response/csv_response.py
cadenzaanalytics/response/data_response.py
cadenzaanalytics/response/enrichment_response.py
cadenzaanalytics/response/error_response.py
cadenzaanalytics/response/extension_data_response.py
cadenzaanalytics/response/extension_response.py
cadenzaanalytics/response/image_response.py
cadenzaanalytics/response/missing_metadata_strategy.py
cadenzaanalytics/response/text_response.py
cadenzaanalytics/response/url_response.py
cadenzaanalytics/version.py
cadenzaanalytics-10.4.0.dist-info/METADATA
cadenzaanalytics-10.4.0.dist-info/WHEEL
cadenzaanalytics-10.4.0.dist-info/licenses/LICENSE.md
cadenzaanalytics-10.4.0.dist-info/RECORD
