Metadata-Version: 2.4
Name: cadenzaanalytics
Version: 10.4.0
Summary: Official Python Package for creation of disy Cadenza analytics extensions
License: Apache-2.0
License-File: LICENSE.md
Author: Disy Informationssysteme GmbH
Author-email: cadenza-analytics@disy.net
Requires-Python: >=3.12,<4.0
Classifier: Development Status :: 5 - Production/Stable
Classifier: Intended Audience :: Developers
Classifier: Intended Audience :: Science/Research
Classifier: License :: OSI Approved :: Apache Software License
Classifier: Natural Language :: English
Classifier: Programming Language :: Python
Classifier: Programming Language :: Python :: 3
Classifier: Programming Language :: Python :: 3.12
Classifier: Programming Language :: Python :: 3.13
Classifier: Programming Language :: Python :: 3.14
Classifier: Topic :: Scientific/Engineering
Requires-Dist: Flask (==3.1.2)
Requires-Dist: Flask-Cors (==6.0.1)
Requires-Dist: Shapely (==2.1.2)
Requires-Dist: Werkzeug (==3.1.4)
Requires-Dist: chardet (==5.2.0)
Requires-Dist: pandas (>=2.0.2,<3.0.0)
Requires-Dist: requests-toolbelt (==1.0.0)
Project-URL: Repository, https://github.com/DisyInformationssysteme/cadenza-analytics-python
